code/Verilog_Test/PE.v
module PE (
    input wire clk,
    input wire reset,
    input wire output_stationary,
    input wire [63:0] in_top,
    input wire [63:0] in_left,
    output reg [63:0] out_right,
    output reg [63:0] out_bottom,
    input wire preload_valid,
    input wire [63:0] preload_data
);

    reg [63:0] preload_buffer;
    reg [63:0] accumulator_buffer;
    reg drain_value_sent;
    
    real in_top_real, in_left_real, preload_real;
    real accumulator_real, result_real;
    
    always @(posedge clk or posedge reset) begin
        if (reset) begin
            preload_buffer <= 64'h0;
            accumulator_buffer <= 64'h0;
            out_right <= 64'h0;
            out_bottom <= 64'h0;
            drain_value_sent <= 1'b0;
        end else begin
            if (output_stationary) begin
                if (preload_valid) begin
                    if (!drain_value_sent) begin
                        out_bottom <= accumulator_buffer;
                        drain_value_sent <= 1'b1;
                    end else begin
                        out_bottom <= in_top;
                    end
                    out_right <= 64'h0;
                end else begin
                    in_top_real = $bitstoreal(in_top);
                    in_left_real = $bitstoreal(in_left);
                    accumulator_real = $bitstoreal(accumulator_buffer);
                    result_real = accumulator_real + (in_top_real * in_left_real);
                    accumulator_buffer <= $realtobits(result_real);
                    out_right <= in_left;
                    out_bottom <= in_top;
                    drain_value_sent <= 1'b0;
                end
            end else begin
                if (preload_valid) begin
                    preload_buffer <= preload_data;
                end
                in_left_real = $bitstoreal(in_left);
                preload_real = $bitstoreal(preload_buffer);
                in_top_real = $bitstoreal(in_top);
                result_real = (in_left_real * preload_real) + in_top_real;
                accumulator_buffer <= $realtobits(result_real);
                out_bottom <= accumulator_buffer;
                out_right <= in_left;
                drain_value_sent <= 1'b0;
            end
        end
    end

endmodule

code/Verilog_Test/PE_tb.v
`include "PE.v"

module PE_tb;

    reg clk;
    reg reset;
    reg output_stationary;
    reg [63:0] in_top;
    reg [63:0] in_left;
    wire [63:0] out_right;
    wire [63:0] out_bottom;
    reg preload_valid;
    reg [63:0] preload_data;
    
    PE dut (
        .clk(clk),
        .reset(reset),
        .output_stationary(output_stationary),
        .in_top(in_top),
        .in_left(in_left),
        .out_right(out_right),
        .out_bottom(out_bottom),
        .preload_valid(preload_valid),
        .preload_data(preload_data)
    );
    
    integer i;
    integer errors;
    real expected_output;
    real actual_output;
    real diff;
    
    initial begin
        clk = 0;
        forever #5 clk = ~clk;
    end
    
    initial begin
        $dumpfile("pe_test.vcd");
        $dumpvars(0, PE_tb);
        
        // Dump individual real values for better waveform viewing
        $dumpvars(1, dut.in_top_real);
        $dumpvars(1, dut.in_left_real);
        $dumpvars(1, dut.preload_real);
        $dumpvars(1, dut.accumulator_real);
        $dumpvars(1, dut.result_real);
        
        $display("=======================================================");
        $display("              PE Module Testbench");
        $display("=======================================================");
        
        errors = 0;
        reset = 1;
        output_stationary = 0;
        in_top = 0;
        in_left = 0;
        preload_valid = 0;
        preload_data = 0;
        
        #20;
        reset = 0;
        #20;
        
        // TEST 1: Weight Stationary Mode - Basic MAC Operation
        $display("\n-------------------------------------------------------");
        $display("TEST 1: Weight Stationary Mode - Basic MAC");
        $display("-------------------------------------------------------");
        
        output_stationary = 0;
        
        // Preload weight
        @(posedge clk);
        preload_valid = 1;
        preload_data = $realtobits(2.0);
        
        @(posedge clk);
        preload_valid = 0;
        
        $display("Preloaded weight = 2.0");
        
        // Perform MAC operations
        for (i = 1; i <= 5; i = i + 1) begin
            @(posedge clk);
            in_left = $realtobits(i * 1.0);
            in_top = $realtobits(i * 0.5);
            
            @(posedge clk);
            #1;
            
            expected_output = (i * 1.0) * 2.0 + (i * 0.5);
            actual_output = $bitstoreal(out_bottom);
            diff = expected_output - actual_output;
            if (diff < 0) diff = -diff;
            
            if (diff > 0.0001) begin
                $display("ERROR cycle %0d: Expected %f, Got %f", i, expected_output, actual_output);
                errors = errors + 1;
            end else begin
                $display("PASS cycle %0d: in_left=%f * weight=2.0 + in_top=%f = %f", 
                         i, i*1.0, i*0.5, actual_output);
            end
            
            // Check that left value propagates to right
            if (out_right !== in_left) begin
                $display("ERROR: out_right should equal in_left");
                errors = errors + 1;
            end
        end
        
        if (errors == 0) begin
            $display("\nTEST 1 PASSED: Weight Stationary MAC operations correct");
        end else begin
            $display("\nTEST 1 FAILED: %0d errors found", errors);
        end
        
        // TEST 2: Weight Stationary - Weight Update
        $display("\n-------------------------------------------------------");
        $display("TEST 2: Weight Stationary - Weight Update");
        $display("-------------------------------------------------------");
        
        errors = 0;
        reset = 1;
        #10;
        reset = 0;
        #10;
        
        output_stationary = 0;
        
        // Preload first weight
        @(posedge clk);
        preload_valid = 1;
        preload_data = $realtobits(3.0);
        
        @(posedge clk);
        preload_valid = 0;
        in_left = $realtobits(2.0);
        in_top = $realtobits(1.0);
        
        @(posedge clk);
        #1;
        
        expected_output = 2.0 * 3.0 + 1.0;
        actual_output = $bitstoreal(out_bottom);
        diff = expected_output - actual_output;
        if (diff < 0) diff = -diff;
        
        if (diff > 0.0001) begin
            $display("ERROR with weight 3.0: Expected %f, Got %f", expected_output, actual_output);
            errors = errors + 1;
        end else begin
            $display("PASS with weight 3.0: Result = %f", actual_output);
        end
        
        // Update weight
        @(posedge clk);
        preload_valid = 1;
        preload_data = $realtobits(5.0);
        
        @(posedge clk);
        preload_valid = 0;
        in_left = $realtobits(2.0);
        in_top = $realtobits(1.0);
        
        @(posedge clk);
        #1;
        
        expected_output = 2.0 * 5.0 + 1.0;
        actual_output = $bitstoreal(out_bottom);
        diff = expected_output - actual_output;
        if (diff < 0) diff = -diff;
        
        if (diff > 0.0001) begin
            $display("ERROR with weight 5.0: Expected %f, Got %f", expected_output, actual_output);
            errors = errors + 1;
        end else begin
            $display("PASS with weight 5.0: Result = %f", actual_output);
        end
        
        if (errors == 0) begin
            $display("\nTEST 2 PASSED: Weight update works correctly");
        end else begin
            $display("\nTEST 2 FAILED: %0d errors found", errors);
        end
        
        // TEST 3: Output Stationary Mode - Accumulation
        $display("\n-------------------------------------------------------");
        $display("TEST 3: Output Stationary Mode - Accumulation");
        $display("-------------------------------------------------------");
        
        errors = 0;
        reset = 1;
        in_left = 64'h0;
        in_top = 64'h0;
        #10;
        reset = 0;
        
        @(posedge clk);
        
        output_stationary = 1;
        preload_valid = 0;
        
        $display("Accumulating products...");
        
        // Accumulate: 1*2 + 2*3 + 3*4 = 2 + 6 + 12 = 20
        @(posedge clk);
        in_left = $realtobits(1.0);
        in_top = $realtobits(2.0);
        
        @(posedge clk);
        in_left = $realtobits(2.0);
        in_top = $realtobits(3.0);
        
        @(posedge clk);
        in_left = $realtobits(3.0);
        in_top = $realtobits(4.0);

        @(posedge clk);
        in_left = 64'h0;
        in_top = 64'h0;
        
        @(posedge clk);
        preload_valid = 1;
        in_left = 64'h0;
        in_top = 64'h0;
        
        #1;
        
        expected_output = 20.0;
        actual_output = $bitstoreal(out_bottom);
        diff = expected_output - actual_output;
        if (diff < 0) diff = -diff;
        
        if (diff > 0.0001) begin
            $display("ERROR: Expected accumulated value %f, Got %f", expected_output, actual_output);
            errors = errors + 1;
        end else begin
            $display("PASS: Accumulated value = %f (expected %f)", actual_output, expected_output);
        end
        
        if (errors == 0) begin
            $display("\nTEST 3 PASSED: Output Stationary accumulation correct");
        end else begin
            $display("\nTEST 3 FAILED: %0d errors found", errors);
        end
        
        // TEST 4: Output Stationary - Multiple Accumulation Cycles
        $display("\n-------------------------------------------------------");
        $display("TEST 4: Output Stationary - Multiple Accumulations");
        $display("-------------------------------------------------------");
        
        errors = 0;
        reset = 1;
        #10;
        reset = 0;
        #10;
        
        output_stationary = 1;
        preload_valid = 0;
        
        // First accumulation: 5*2 = 10
        @(posedge clk);
        in_left = $realtobits(5.0);
        in_top = $realtobits(2.0);
        
        @(posedge clk);
        in_left = 64'h0;
        in_top = 64'h0;
        
        @(posedge clk);
        preload_valid = 1;
        in_left = 64'h0;
        in_top = 64'h0;
        
        #1;
        
        actual_output = $bitstoreal(out_bottom);
        if ((actual_output - 10.0) > 0.0001 || (actual_output - 10.0) < -0.0001) begin
            $display("ERROR: First accumulation - Expected 10.0, Got %f", actual_output);
            errors = errors + 1;
        end else begin
            $display("PASS: First accumulation = %f", actual_output);
        end
        
        // Reset for second accumulation
        reset = 1;
        #10;
        reset = 0;
        #10;
        
        preload_valid = 0;
        
        // Second accumulation: 3*4 + 2*1 = 12 + 2 = 14
        @(posedge clk);
        in_left = $realtobits(3.0);
        in_top = $realtobits(4.0);
        
        @(posedge clk);
        in_left = $realtobits(2.0);
        in_top = $realtobits(1.0);
        
        @(posedge clk);
        in_left = 64'h0;
        in_top = 64'h0;
        
        @(posedge clk);
        preload_valid = 1;
        in_left = 64'h0;
        in_top = 64'h0;
        
        #1;
        
        actual_output = $bitstoreal(out_bottom);
        if ((actual_output - 14.0) > 0.0001 || (actual_output - 14.0) < -0.0001) begin
            $display("ERROR: Second accumulation - Expected 14.0, Got %f", actual_output);
            errors = errors + 1;
        end else begin
            $display("PASS: Second accumulation = %f", actual_output);
        end
        
        if (errors == 0) begin
            $display("\nTEST 4 PASSED: Multiple accumulation cycles work correctly");
        end else begin
            $display("\nTEST 4 FAILED: %0d errors found", errors);
        end
        
        // TEST 5: Zero Input Handling
        $display("\n-------------------------------------------------------");
        $display("TEST 5: Zero Input Handling");
        $display("-------------------------------------------------------");
        
        errors = 0;
        reset = 1;
        #10;
        reset = 0;
        #10;
        
        output_stationary = 0;
        
        @(posedge clk);
        preload_valid = 1;
        preload_data = $realtobits(7.0);
        
        @(posedge clk);
        preload_valid = 0;
        in_left = 64'h0;
        in_top = 64'h0;
        
        @(posedge clk);
        #1;
        
        actual_output = $bitstoreal(out_bottom);
        if (actual_output != 0.0) begin
            $display("ERROR: Zero inputs should give 0, Got %f", actual_output);
            errors = errors + 1;
        end else begin
            $display("PASS: Zero inputs correctly produce 0");
        end
        
        if (errors == 0) begin
            $display("\nTEST 5 PASSED: Zero input handling correct");
        end else begin
            $display("\nTEST 5 FAILED: %0d errors found", errors);
        end
        
        // TEST 6: Negative Number Handling
        $display("\n-------------------------------------------------------");
        $display("TEST 6: Negative Number Handling");
        $display("-------------------------------------------------------");
        
        errors = 0;
        reset = 1;
        #10;
        reset = 0;
        #10;
        
        output_stationary = 0;
        
        @(posedge clk);
        preload_valid = 1;
        preload_data = $realtobits(-2.0);
        
        @(posedge clk);
        preload_valid = 0;
        in_left = $realtobits(3.0);
        in_top = $realtobits(1.0);
        
        @(posedge clk);
        #1;
        
        expected_output = 3.0 * (-2.0) + 1.0;  // -6 + 1 = -5
        actual_output = $bitstoreal(out_bottom);
        diff = expected_output - actual_output;
        if (diff < 0) diff = -diff;
        
        if (diff > 0.0001) begin
            $display("ERROR: Expected %f, Got %f", expected_output, actual_output);
            errors = errors + 1;
        end else begin
            $display("PASS: Negative weight handled correctly: %f", actual_output);
        end
        
        // Test with negative input
        @(posedge clk);
        in_left = $realtobits(-4.0);
        in_top = $realtobits(2.0);
        
        @(posedge clk);
        #1;
        
        expected_output = (-4.0) * (-2.0) + 2.0;  // 8 + 2 = 10
        actual_output = $bitstoreal(out_bottom);
        diff = expected_output - actual_output;
        if (diff < 0) diff = -diff;
        
        if (diff > 0.0001) begin
            $display("ERROR: Expected %f, Got %f", expected_output, actual_output);
            errors = errors + 1;
        end else begin
            $display("PASS: Negative input handled correctly: %f", actual_output);
        end
        
        if (errors == 0) begin
            $display("\nTEST 6 PASSED: Negative number handling correct");
        end else begin
            $display("\nTEST 6 FAILED: %0d errors found", errors);
        end
        
        #100;
        
        $display("\n=======================================================");
        $display("            PE Module Tests Completed");
        $display("=======================================================\n");
        
        $finish;
    end
    
    initial begin
        #50000;
        $display("\nERROR: Testbench timeout!");
        $finish;
    end

endmodule

code/Verilog_Test/pe_test.vcd
$date
	Tue Dec  2 11:03:50 2025
$end
$version
	Icarus Verilog
$end
$timescale
	1s
$end
$scope module PE_tb $end
$var wire 64 ! out_right [63:0] $end
$var wire 64 " out_bottom [63:0] $end
$var reg 1 # clk $end
$var reg 64 $ in_left [63:0] $end
$var reg 64 % in_top [63:0] $end
$var reg 1 & output_stationary $end
$var reg 64 ' preload_data [63:0] $end
$var reg 1 ( preload_valid $end
$var reg 1 ) reset $end
$var real 1 * actual_output $end
$var real 1 + diff $end
$var integer 32 , errors [31:0] $end
$var real 1 - expected_output $end
$var integer 32 . i [31:0] $end
$scope module dut $end
$var wire 1 # clk $end
$var wire 64 / in_left [63:0] $end
$var wire 64 0 in_top [63:0] $end
$var wire 1 & output_stationary $end
$var wire 64 1 preload_data [63:0] $end
$var wire 1 ( preload_valid $end
$var wire 1 ) reset $end
$var reg 64 2 accumulator_buffer [63:0] $end
$var reg 1 3 drain_value_sent $end
$var reg 64 4 out_bottom [63:0] $end
$var reg 64 5 out_right [63:0] $end
$var reg 64 6 preload_buffer [63:0] $end
$var real 1 7 accumulator_real $end
$var real 1 8 in_left_real $end
$var real 1 9 in_top_real $end
$var real 1 : preload_real $end
$var real 1 ; result_real $end
$upscope $end
$upscope $end
$enddefinitions $end
$comment Show the parameter values. $end
$dumpall
$end
#0
$dumpvars
r0 ;
r0 :
r0 9
r0 8
r0 7
b0 6
b0 5
b0 4
03
b0 2
b0 1
b0 0
b0 /
bx .
r0 -
b0 ,
r0 +
r0 *
1)
0(
b0 '
0&
b0 %
b0 $
0#
b0 "
b0 !
$end
#5
1#
#10
0#
#15
1#
#20
0#
0)
#25
1#
#30
0#
#35
1#
#40
0#
#45
b100000000000000000000000000000000000000000000000000000000000000 6
b100000000000000000000000000000000000000000000000000000000000000 '
b100000000000000000000000000000000000000000000000000000000000000 1
1(
1#
#50
0#
#55
r2 :
b1 .
0(
1#
#60
0#
#65
b11111111110000000000000000000000000000000000000000000000000000 !
b11111111110000000000000000000000000000000000000000000000000000 5
b100000000000100000000000000000000000000000000000000000000000000 2
r2.5 ;
r0.5 9
r1 8
b11111111100000000000000000000000000000000000000000000000000000 %
b11111111100000000000000000000000000000000000000000000000000000 0
b11111111110000000000000000000000000000000000000000000000000000 $
b11111111110000000000000000000000000000000000000000000000000000 /
1#
#70
0#
#75
b100000000000100000000000000000000000000000000000000000000000000 "
b100000000000100000000000000000000000000000000000000000000000000 4
1#
#76
b10 .
r2.5 *
r2.5 -
#80
0#
#85
b100000000000000000000000000000000000000000000000000000000000000 !
b100000000000000000000000000000000000000000000000000000000000000 5
b100000000010100000000000000000000000000000000000000000000000000 2
r5 ;
r1 9
r2 8
b11111111110000000000000000000000000000000000000000000000000000 %
b11111111110000000000000000000000000000000000000000000000000000 0
b100000000000000000000000000000000000000000000000000000000000000 $
b100000000000000000000000000000000000000000000000000000000000000 /
1#
#90
0#
#95
b100000000010100000000000000000000000000000000000000000000000000 "
b100000000010100000000000000000000000000000000000000000000000000 4
1#
#96
b11 .
r5 *
r5 -
#100
0#
#105
b100000000001000000000000000000000000000000000000000000000000000 !
b100000000001000000000000000000000000000000000000000000000000000 5
b100000000011110000000000000000000000000000000000000000000000000 2
r7.5 ;
r1.5 9
r3 8
b11111111111000000000000000000000000000000000000000000000000000 %
b11111111111000000000000000000000000000000000000000000000000000 0
b100000000001000000000000000000000000000000000000000000000000000 $
b100000000001000000000000000000000000000000000000000000000000000 /
1#
#110
0#
#115
b100000000011110000000000000000000000000000000000000000000000000 "
b100000000011110000000000000000000000000000000000000000000000000 4
1#
#116
b100 .
r7.5 *
r7.5 -
#120
0#
#125
b100000000010000000000000000000000000000000000000000000000000000 !
b100000000010000000000000000000000000000000000000000000000000000 5
b100000000100100000000000000000000000000000000000000000000000000 2
r10 ;
r2 9
r4 8
b100000000000000000000000000000000000000000000000000000000000000 %
b100000000000000000000000000000000000000000000000000000000000000 0
b100000000010000000000000000000000000000000000000000000000000000 $
b100000000010000000000000000000000000000000000000000000000000000 /
1#
#130
0#
#135
b100000000100100000000000000000000000000000000000000000000000000 "
b100000000100100000000000000000000000000000000000000000000000000 4
1#
#136
b101 .
r10 *
r10 -
#140
0#
#145
b100000000010100000000000000000000000000000000000000000000000000 !
b100000000010100000000000000000000000000000000000000000000000000 5
b100000000101001000000000000000000000000000000000000000000000000 2
r12.5 ;
r2.5 9
r5 8
b100000000000100000000000000000000000000000000000000000000000000 %
b100000000000100000000000000000000000000000000000000000000000000 0
b100000000010100000000000000000000000000000000000000000000000000 $
b100000000010100000000000000000000000000000000000000000000000000 /
1#
#150
0#
#155
b100000000101001000000000000000000000000000000000000000000000000 "
b100000000101001000000000000000000000000000000000000000000000000 4
1#
#156
b0 "
b0 4
b0 !
b0 5
b0 2
b0 6
1)
b110 .
r12.5 *
r12.5 -
#160
0#
#165
1#
#166
0)
#170
0#
#175
b100000000010100000000000000000000000000000000000000000000000000 !
b100000000010100000000000000000000000000000000000000000000000000 5
b100000000000100000000000000000000000000000000000000000000000000 2
r2.5 ;
r0 :
1#
#180
0#
#185
b100000000000100000000000000000000000000000000000000000000000000 "
b100000000000100000000000000000000000000000000000000000000000000 4
b100000000001000000000000000000000000000000000000000000000000000 6
b100000000001000000000000000000000000000000000000000000000000000 '
b100000000001000000000000000000000000000000000000000000000000000 1
1(
1#
#190
0#
#195
b100000000000000000000000000000000000000000000000000000000000000 !
b100000000000000000000000000000000000000000000000000000000000000 5
b100000000011100000000000000000000000000000000000000000000000000 2
r7 ;
r1 9
r3 :
r2 8
b11111111110000000000000000000000000000000000000000000000000000 %
b11111111110000000000000000000000000000000000000000000000000000 0
b100000000000000000000000000000000000000000000000000000000000000 $
b100000000000000000000000000000000000000000000000000000000000000 /
0(
1#
#200
0#
#205
b100000000011100000000000000000000000000000000000000000000000000 "
b100000000011100000000000000000000000000000000000000000000000000 4
1#
#206
r7 *
r7 -
#210
0#
#215
b100000000010100000000000000000000000000000000000000000000000000 6
b100000000010100000000000000000000000000000000000000000000000000 '
b100000000010100000000000000000000000000000000000000000000000000 1
1(
1#
#220
0#
#225
b100000000100110000000000000000000000000000000000000000000000000 2
r11 ;
r5 :
0(
1#
#230
0#
#235
b100000000100110000000000000000000000000000000000000000000000000 "
b100000000100110000000000000000000000000000000000000000000000000 4
1#
#236
b0 "
b0 4
b0 !
b0 5
b0 2
b0 6
b0 %
b0 0
b0 $
b0 /
1)
r11 *
r11 -
#240
0#
#245
1#
#246
0)
#250
0#
#255
r0 ;
r0 8
r0 9
1&
1#
#260
0#
#265
b100000000000000000000000000000000000000000000000000000000000000 "
b100000000000000000000000000000000000000000000000000000000000000 4
b11111111110000000000000000000000000000000000000000000000000000 !
b11111111110000000000000000000000000000000000000000000000000000 5
b100000000000000000000000000000000000000000000000000000000000000 2
r2 ;
r1 8
r2 9
b100000000000000000000000000000000000000000000000000000000000000 %
b100000000000000000000000000000000000000000000000000000000000000 0
b11111111110000000000000000000000000000000000000000000000000000 $
b11111111110000000000000000000000000000000000000000000000000000 /
1#
#270
0#
#275
b100000000001000000000000000000000000000000000000000000000000000 "
b100000000001000000000000000000000000000000000000000000000000000 4
b100000000000000000000000000000000000000000000000000000000000000 !
b100000000000000000000000000000000000000000000000000000000000000 5
b100000000100000000000000000000000000000000000000000000000000000 2
r8 ;
r2 7
r2 8
r3 9
b100000000001000000000000000000000000000000000000000000000000000 %
b100000000001000000000000000000000000000000000000000000000000000 0
b100000000000000000000000000000000000000000000000000000000000000 $
b100000000000000000000000000000000000000000000000000000000000000 /
1#
#280
0#
#285
b100000000010000000000000000000000000000000000000000000000000000 "
b100000000010000000000000000000000000000000000000000000000000000 4
b100000000001000000000000000000000000000000000000000000000000000 !
b100000000001000000000000000000000000000000000000000000000000000 5
b100000000110100000000000000000000000000000000000000000000000000 2
r20 ;
r8 7
r3 8
r4 9
b100000000010000000000000000000000000000000000000000000000000000 %
b100000000010000000000000000000000000000000000000000000000000000 0
b100000000001000000000000000000000000000000000000000000000000000 $
b100000000001000000000000000000000000000000000000000000000000000 /
1#
#290
0#
#295
b0 "
b0 4
b0 !
b0 5
r20 7
r0 8
r0 9
b0 %
b0 0
b0 $
b0 /
1#
#300
0#
#305
13
b100000000110100000000000000000000000000000000000000000000000000 "
b100000000110100000000000000000000000000000000000000000000000000 4
1(
1#
#306
03
b0 "
b0 4
b0 2
1)
r20 *
r20 -
#310
0#
#315
1#
#316
0)
#320
0#
#325
13
1#
#326
0(
#330
0#
#335
03
b100000000000000000000000000000000000000000000000000000000000000 "
b100000000000000000000000000000000000000000000000000000000000000 4
b100000000010100000000000000000000000000000000000000000000000000 !
b100000000010100000000000000000000000000000000000000000000000000 5
b100000000100100000000000000000000000000000000000000000000000000 2
r10 ;
r0 7
r5 8
r2 9
b100000000000000000000000000000000000000000000000000000000000000 %
b100000000000000000000000000000000000000000000000000000000000000 0
b100000000010100000000000000000000000000000000000000000000000000 $
b100000000010100000000000000000000000000000000000000000000000000 /
1#
#340
0#
#345
b0 "
b0 4
b0 !
b0 5
r10 7
r0 8
r0 9
b0 %
b0 0
b0 $
b0 /
1#
#350
0#
#355
13
b100000000100100000000000000000000000000000000000000000000000000 "
b100000000100100000000000000000000000000000000000000000000000000 4
1(
1#
#356
03
b0 "
b0 4
b0 2
1)
r10 *
#360
0#
#365
1#
#366
0)
#370
0#
#375
13
1#
#376
0(
#380
0#
#385
03
b100000000010000000000000000000000000000000000000000000000000000 "
b100000000010000000000000000000000000000000000000000000000000000 4
b100000000001000000000000000000000000000000000000000000000000000 !
b100000000001000000000000000000000000000000000000000000000000000 5
b100000000101000000000000000000000000000000000000000000000000000 2
r12 ;
r0 7
r3 8
r4 9
b100000000010000000000000000000000000000000000000000000000000000 %
b100000000010000000000000000000000000000000000000000000000000000 0
b100000000001000000000000000000000000000000000000000000000000000 $
b100000000001000000000000000000000000000000000000000000000000000 /
1#
#390
0#
#395
b11111111110000000000000000000000000000000000000000000000000000 "
b11111111110000000000000000000000000000000000000000000000000000 4
b100000000000000000000000000000000000000000000000000000000000000 !
b100000000000000000000000000000000000000000000000000000000000000 5
b100000000101100000000000000000000000000000000000000000000000000 2
r14 ;
r12 7
r2 8
r1 9
b11111111110000000000000000000000000000000000000000000000000000 %
b11111111110000000000000000000000000000000000000000000000000000 0
b100000000000000000000000000000000000000000000000000000000000000 $
b100000000000000000000000000000000000000000000000000000000000000 /
1#
#400
0#
#405
b0 "
b0 4
b0 !
b0 5
r14 7
r0 8
r0 9
b0 %
b0 0
b0 $
b0 /
1#
#410
0#
#415
13
b100000000101100000000000000000000000000000000000000000000000000 "
b100000000101100000000000000000000000000000000000000000000000000 4
1(
1#
#416
03
b0 "
b0 4
b0 2
1)
r14 *
#420
0#
#425
1#
#426
0)
#430
0#
#435
13
1#
#436
0&
#440
0#
#445
03
b100000000011100000000000000000000000000000000000000000000000000 6
r0 ;
r0 :
b100000000011100000000000000000000000000000000000000000000000000 '
b100000000011100000000000000000000000000000000000000000000000000 1
1#
#450
0#
#455
r7 :
0(
1#
#460
0#
#465
1#
#466
b0 6
1)
r0 *
#470
0#
#475
1#
#476
0)
#480
0#
#485
r0 :
1#
#490
0#
#495
b1100000000000000000000000000000000000000000000000000000000000000 6
b1100000000000000000000000000000000000000000000000000000000000000 '
b1100000000000000000000000000000000000000000000000000000000000000 1
1(
1#
#500
0#
#505
b100000000001000000000000000000000000000000000000000000000000000 !
b100000000001000000000000000000000000000000000000000000000000000 5
b1100000000010100000000000000000000000000000000000000000000000000 2
r-5 ;
r1 9
r-2 :
r3 8
b11111111110000000000000000000000000000000000000000000000000000 %
b11111111110000000000000000000000000000000000000000000000000000 0
b100000000001000000000000000000000000000000000000000000000000000 $
b100000000001000000000000000000000000000000000000000000000000000 /
0(
1#
#510
0#
#515
b1100000000010100000000000000000000000000000000000000000000000000 "
b1100000000010100000000000000000000000000000000000000000000000000 4
1#
#516
r-5 *
r-5 -
#520
0#
#525
b1100000000010000000000000000000000000000000000000000000000000000 !
b1100000000010000000000000000000000000000000000000000000000000000 5
b100000000100100000000000000000000000000000000000000000000000000 2
r10 ;
r2 9
r-4 8
b100000000000000000000000000000000000000000000000000000000000000 %
b100000000000000000000000000000000000000000000000000000000000000 0
b1100000000010000000000000000000000000000000000000000000000000000 $
b1100000000010000000000000000000000000000000000000000000000000000 /
1#
#530
0#
#535
b100000000100100000000000000000000000000000000000000000000000000 "
b100000000100100000000000000000000000000000000000000000000000000 4
1#
#536
r10 *
r10 -
